fetch_deepl/__init__.py
fetch_deepl/__main__.py-
fetch_deepl/fetch_deepl.py
fetch_deepl-0.1.2.dist-info/entry_points.txt
fetch_deepl-0.1.2.dist-info/LICENSE
fetch_deepl-0.1.2.dist-info/WHEEL
fetch_deepl-0.1.2.dist-info/METADATA
fetch_deepl-0.1.2.dist-info/RECORD
